LICENSE
MANIFEST.in
NOTICE.md
README.md
pytest.ini
requirements-docs.txt
requirements-test.txt
requirements.txt
setup.py
tox.ini
steenzout/__init__.py
steenzout.serialization.json.egg-info/PKG-INFO
steenzout.serialization.json.egg-info/SOURCES.txt
steenzout.serialization.json.egg-info/dependency_links.txt
steenzout.serialization.json.egg-info/namespace_packages.txt
steenzout.serialization.json.egg-info/requires.txt
steenzout.serialization.json.egg-info/top_level.txt
steenzout/serialization/__init__.py
steenzout/serialization/json/__init__.py
steenzout/serialization/json/encoders.py
steenzout/serialization/json/metadata.py
tests/__init__.py
tests/json_test.py
tests/version_test.py