Metadata-Version: 1.2
Name: steenzout.serialization.json
Version: 1.0.8
Summary: Steenzout JSON serialization package.
Home-page: https://github.com/steenzout/python-serialization-json
Author: Pedro Salgado
Author-email: steenzout@ymail.com
Maintainer: Pedro Salgado
Maintainer-email: steenzout@ymail.com
License: Apache 2.0
Platform: UNKNOWN
Classifier: Development Status :: 5 - Production/Stable
Classifier: Intended Audience :: Developers
Classifier: Natural Language :: English
Classifier: License :: OSI Approved :: Apache Software License
Classifier: Programming Language :: Python
Classifier: Programming Language :: Python :: 2.7
Classifier: Programming Language :: Python :: 3
Classifier: Programming Language :: Python :: 3.5
Classifier: Programming Language :: Python :: 3.6
Classifier: Programming Language :: Python :: 3.7
Classifier: Programming Language :: Python :: Implementation :: CPython
Classifier: Programming Language :: Python :: Implementation :: PyPy
